restart/__init__.py
restart/base.py
restart/data.py
restart/demand.py
restart/demand_dict.py
restart/demand_jhu.py
restart/demand_mitre.py
restart/demand_who.py
restart/epi.py
restart/epi_dict.py
restart/epi_table.py
restart/filtermodel.py
restart/financial.py
restart/financial_dict.py
restart/financial_table.py
restart/inventory.py
restart/inventory_dict.py
restart/load.py
restart/load_csv.py
restart/log.py
restart/main.py
restart/mobility.py
restart/mobility_dict.py
restart/mobility_table.py
restart/model.py
restart/module_test.py
restart/organization.py
restart/organization_dict.py
restart/output.py
restart/population.py
restart/population_dict.py
restart/population_oes.py
restart/population_wa.py
restart/resource_dict.py
restart/resourcemodel.py
restart/restart.py
restart/util.py
restart/validate.py
restart/config/ca-vent/config.yaml
restart/config/config-v1.1/config.yaml
restart/config/default/config.yaml
restart/config/des/config.yaml
restart/config/jhu/config.yaml
restart/config/seattle/ItemAnalysis.xlsx
restart/config/seattle/Model_Input_Seattle_Example.xlsx
restart/config/seattle/NOTOUCH_Critical Supply Dashboard_19 items.xlsx
restart/config/seattle/PLAY_Critical Supply Dashboard_19 items copy.xlsx
restart/config/sj/config.yaml
restart/config/vuln/config.yaml
restart/config/vuln/config.yaml.tmp
restart/config/wa/config.yaml
restart/config/wa_groups/config.yaml
restart-2.6.7.dist-info/METADATA
restart-2.6.7.dist-info/WHEEL
restart-2.6.7.dist-info/top_level.txt
restart-2.6.7.dist-info/RECORD
